baremetalml/__init__.py
baremetalml/base/__init__.py
baremetalml/base/model.py
baremetalml/base/transformer.py
baremetalml/linear/__init__.py
baremetalml/linear/linear_regression.py
baremetalml/linear/logistic_regression.py
baremetalml/neighbours/__init__.py
baremetalml/neighbours/knn_classifier.py
baremetalml/neighbours/knn_regressor.py
baremetalml/preprocessing/__init__.py
baremetalml/preprocessing/label_encoder.py
baremetalml/preprocessing/normal_scaler.py
baremetalml/preprocessing/one_hot_encoder.py
baremetalml/preprocessing/polynomial_features.py
baremetalml/preprocessing/standard_scaler.py
baremetalml-1.0.0.dist-info/licenses/LICENSE
baremetalml-1.0.0.dist-info/METADATA
baremetalml-1.0.0.dist-info/WHEEL
baremetalml-1.0.0.dist-info/top_level.txt
baremetalml-1.0.0.dist-info/RECORD
