Metadata-Version: 2.4
Name: baremetalml
Version: 1.0.0
Summary: Lightweight modular ML library from scratch in Python
Home-page: https://github.com/AskariAbidi18/ML_from_Scratch
Author: Askari Abidi
Author-email: askari.abidi.2005@gmail.com
License: MIT
Keywords: machine learning,ML,numpy,educational,baremetalml
Classifier: Programming Language :: Python :: 3
Classifier: License :: OSI Approved :: MIT License
Classifier: Operating System :: OS Independent
Classifier: Intended Audience :: Education
Classifier: Topic :: Scientific/Engineering :: Artificial Intelligence
Requires-Python: >=3.8
License-File: LICENSE
Requires-Dist: numpy>=1.24.0
Dynamic: author
Dynamic: author-email
Dynamic: classifier
Dynamic: description
Dynamic: description-content-type
Dynamic: home-page
Dynamic: keywords
Dynamic: license
Dynamic: license-file
Dynamic: requires-dist
Dynamic: requires-python
Dynamic: summary
